android_manager/__init__.py
android_manager/__main__.py
android_manager/caller.py
android_manager/downloader.py
android_manager/dependencies/__init__.py
android_manager/dependencies/favicon.ico
android_manager/translations/__init__.py
android_manager/translations/中文.json
python_android_manager-3.3.dist-info/METADATA
python_android_manager-3.3.dist-info/WHEEL
python_android_manager-3.3.dist-info/entry_points.txt
python_android_manager-3.3.dist-info/top_level.txt
python_android_manager-3.3.dist-info/RECORD
