Metadata-Version: 2.1
Name: python-android-manager
Version: 3.3
Summary: Python Android Manager
Home-page: https://wufan.fun/
Author: Fan Wu
Author-email: admin@wufan.fun
License: UNKNOWN
Project-URL: Source Code, https://github.com/WindowsRegedit/PythonAndroidPhoneManager
Keywords: GUI Android
Platform: UNKNOWN
Classifier: Development Status :: 5 - Production/Stable
Classifier: Intended Audience :: Developers
Classifier: License :: OSI Approved :: MIT License
Classifier: Programming Language :: Python :: 3.5
Classifier: Programming Language :: Python :: 3.6
Classifier: Programming Language :: Python :: 3.7
Classifier: Programming Language :: Python :: 3.8
Classifier: Programming Language :: Python :: 3.9
Requires-Dist: requests (==2.27.1)
Requires-Dist: PyQt5 (==5.15.6)
Requires-Dist: qt-material (==2.12)
